region_profiler/__init__.py
region_profiler/chrome_trace_listener.py
region_profiler/debug_listener.py
region_profiler/global_instance.py
region_profiler/listener.py
region_profiler/node.py
region_profiler/profiler.py
region_profiler/reporter_columns.py
region_profiler/reporters.py
region_profiler/utils.py
region_profiler-0.9.3.data/data/region_profiler/LICENSE.rst
region_profiler-0.9.3.dist-info/LICENSE.rst
region_profiler-0.9.3.dist-info/METADATA
region_profiler-0.9.3.dist-info/WHEEL
region_profiler-0.9.3.dist-info/top_level.txt
region_profiler-0.9.3.dist-info/RECORD
