Metadata-Version: 2.1
Name: region-profiler
Version: 0.9.3
Summary: Profile user-defined regions of code without any external tools
Home-page: https://github.com/metopa/region_profiler
Author: Viacheslav Kroilov
Author-email: slavakroilov@gmail.com
License: MIT
Keywords: timing,timer,profiling,profiler
Platform: UNKNOWN
Classifier: Development Status :: 4 - Beta
Classifier: Intended Audience :: Developers
Classifier: License :: OSI Approved :: MIT License
Classifier: Operating System :: OS Independent
Classifier: Programming Language :: Python
Classifier: Programming Language :: Python :: 3
Classifier: Programming Language :: Python :: 3.4
Classifier: Programming Language :: Python :: 3.5
Classifier: Programming Language :: Python :: 3.6
Classifier: Programming Language :: Python :: 3.7
Classifier: Topic :: Software Development :: Libraries :: Python Modules
Classifier: Topic :: Software Development :: Quality Assurance
Classifier: Topic :: Utilities
